openautomatumdronedata/__init__.py
openautomatumdronedata/automatumBokehSever.py
openautomatumdronedata/dataset.py
openautomatumdronedata/dynamicWorld.py
openautomatumdronedata/staticWorld.py
openautomatumdronedata-0.5.0.dist-info/METADATA
openautomatumdronedata-0.5.0.dist-info/WHEEL
openautomatumdronedata-0.5.0.dist-info/entry_points.txt
openautomatumdronedata-0.5.0.dist-info/top_level.txt
openautomatumdronedata-0.5.0.dist-info/RECORD
