Metadata-Version: 2.1
Name: openautomatumdronedata
Version: 0.5.0
Summary: A utility package for the open automatum drone dataset
Home-page: https://www.automatum-data.com
Author: Peter Zechel
Author-email: peter.zechel@automatum-data.com
License: CC-BY-SA
Project-URL: Bug Reports, https://bitbucket.org/automatum/open.automatum.dronedata/issues?status=new&status=open
Project-URL: Documentation, https://openautomatumdronedata.readthedocs.io/en/latest/
Project-URL: Source, https://bitbucket.org/automatum/open.automatum.dronedata/src/master/
Classifier: Development Status :: 2 - Pre-Alpha
Classifier: Intended Audience :: Science/Research
Classifier: License :: CC0 1.0 Universal (CC0 1.0) Public Domain Dedication
Classifier: Operating System :: POSIX :: Linux
Classifier: Operating System :: MacOS
Classifier: Operating System :: Microsoft :: Windows
Classifier: Programming Language :: Python :: 3
Requires-Dist: bokeh >2.0.0
